cflint/__init__.py
cflint/__main__.py
cflint/linter.py
cflint/rules/__init__.py
cflint/rules/matching_log_groups_and_sub_filters.py
cflint/rules/missing_endpoint_type.py
cflint/rules/missing_log_retention_period.py
cflint/rules/no_deprecated_lambda_runtimes.py
cflint/rules/no_full_access_policies.py
cflint/rules/no_leading_zeroes.py
cflint/rules/no_missing_log_groups.py
cflint/rules/no_old_style_subscription_filters.py
cflint/rules/no_provisioned_throughput.py
cflint/rules/no_reserved_env_vars.py
cflint/rules/no_reserved_words_in_dynamo_column_names.py
cflint/rules/well_formed_subscription_filters.py
dwcflint-1.2.16.data/scripts/dwcflint
dwcflint-1.2.16.dist-info/LICENSE
dwcflint-1.2.16.dist-info/METADATA
dwcflint-1.2.16.dist-info/WHEEL
dwcflint-1.2.16.dist-info/top_level.txt
dwcflint-1.2.16.dist-info/RECORD
