Metadata-Version: 2.1
Name: dwcflint
Version: 1.2.16
Summary: A collection of extra rules for linting cloudformation files
Home-page: https://github.com/dwtechnologies/dwcflint
Author: Daniel Wellington
Author-email: servicedesk@danielwellington.com
License: UNKNOWN
Platform: UNKNOWN
Classifier: Programming Language :: Python :: 3
Classifier: Operating System :: OS Independent
Classifier: License :: OSI Approved :: GNU General Public License v3 (GPLv3)
Classifier: Programming Language :: Python
Classifier: Environment :: Console
Classifier: Development Status :: 5 - Production/Stable
Classifier: Intended Audience :: Developers
Classifier: Operating System :: POSIX
Classifier: Operating System :: MacOS
Classifier: Topic :: Software Development :: Quality Assurance
Requires-Python: >=3.6
License-File: LICENSE
Requires-Dist: cfn-lint (>=0.54.4)
